xj_common/__init__.py
xj_common/admin.py
xj_common/apps.py
xj_common/models.py
xj_common/service_register.py
xj_common/urls.py
xj_common/validate.py
xj_common/api/__init__.py
xj_common/api/notice_apis.py
xj_common/api/region_api.py
xj_common/api/translate_apis.py
xj_common/apis/__init__.py
xj_common/apis/access_level_apis.py
xj_common/apis/app_versionl_apis.py
xj_common/apis/encyclopedia_api.py
xj_common/apis/module_service_apis.py
xj_common/apis/modules_apis.py
xj_common/apis/notice_apis.py
xj_common/apis/proxy_request_api.py
xj_common/apis/region_api.py
xj_common/apis/rpc_service_manage.py
xj_common/apis/service_manage_api.py
xj_common/apis/translate_apis.py
xj_common/management/__init__.py
xj_common/management/run.py
xj_common/management/commands/__init__.py
xj_common/management/commands/hello_word.py
xj_common/services/__init__.py
xj_common/services/access_level_services.py
xj_common/services/app_version_services.py
xj_common/services/encyclopedia_services.py
xj_common/services/notice_services.py
xj_common/services/public_service.py
xj_common/services/regin_service.py
xj_common/services/translate_server.py
xj_common/services/xj_module_service_services.py
xj_common/services/xj_module_services.py
xj_common/utils/__init__.py
xj_common/utils/custom_authorization.py
xj_common/utils/custom_response.py
xj_common/utils/custom_tool.py
xj_common/utils/get_system_apis.py
xj_common/utils/j_dict.py
xj_common/utils/j_recur.py
xj_common/utils/j_valuation.py
xj_common/utils/join_list.py
xj_common/utils/omnipotence_wrapper.py
xj_common/utils/service_manager.py
xj_common/utils/user_wrapper.py
xj_common/utils/validator.py
xj_common-1.0.27.dist-info/METADATA
xj_common-1.0.27.dist-info/WHEEL
xj_common-1.0.27.dist-info/top_level.txt
xj_common-1.0.27.dist-info/RECORD
