Metadata-Version: 2.1
Name: xj-common
Version: 1.0.27
Summary: 公共模块
Author: 赵向明
Author-email: sky4834@163.com
Maintainer: 孙楷炎
Maintainer-email: sky4834@163.com
License: apache 3.0
